epicenter/__init__.py
epicenter/epicenter.py
epicenter-1.7.dist-info/METADATA
epicenter-1.7.dist-info/WHEEL
epicenter-1.7.dist-info/top_level.txt
epicenter-1.7.dist-info/RECORD
