Metadata-Version: 2.1
Name: epicenter
Version: 1.7
Summary: Python Package for interacting with the Forio Epicenter Platform
Home-page: http://www.forio.com/epicenter
Author: Forio
Author-email: tech@forio.com
License: Apache License 2.0
Keywords: Forio,Epicenter
Platform: UNKNOWN
